machine_learning/recommending/__init__.py
machine_learning/recommending/app.py
machine_learning/recommending/callbacks.py
machine_learning/recommending/data.py
machine_learning/recommending/entrypoint.py
machine_learning/recommending/interface.py
machine_learning/recommending/lit.py
machine_learning/recommending/losses.py
machine_learning/recommending/main.py
machine_learning/recommending/maths.py
machine_learning/recommending/metrics.py
machine_learning/recommending/models/__init__.py
machine_learning/recommending/models/als.py
machine_learning/recommending/models/baseline.py
machine_learning/recommending/models/bpmf.py
machine_learning/recommending/models/cat.py
machine_learning/recommending/models/mf.py
machine_learning/recommending/models/slim.py
machine_learning/recommending/movielens/__init__.py
machine_learning/recommending/movielens/callbacks.py
machine_learning/recommending/movielens/cat.py
machine_learning/recommending/movielens/data.py
machine_learning/recommending/movielens/lit.py
machine_learning/recommending/tests/__init__.py
machine_learning/recommending/tests/conftest.py
machine_learning/recommending/tests/test_callbacks.py
machine_learning/recommending/tests/test_configs.py
machine_learning/recommending/tests/test_data.py
machine_learning/recommending/tests/test_losses.py
machine_learning/recommending/tests/test_main.py
machine_learning/recommending/tests/test_math.py
machine_learning/recommending/tests/test_metrics.py
machine_learning/recommending/tests/test_models.py
machine_learning/recommending/tests/text_extras.py
machine_learning/recommending/utils.py
my_tools/__init__.py
my_tools/entrypoint.py
my_tools/models.py
my_tools/utils.py
ysda-0.1.16.dist-info/LICENSE
ysda-0.1.16.dist-info/WHEEL
ysda-0.1.16.dist-info/METADATA
ysda-0.1.16.dist-info/RECORD
