Metadata-Version: 2.1
Name: ysda
Version: 0.1.16
Summary: 
Author: DimaKoshman
Author-email: koshmandk@yandex.ru
Requires-Python: >=3.8,<3.9
Classifier: Programming Language :: Python :: 3
Classifier: Programming Language :: Python :: 3.8
Requires-Dist: aenum (>=3.1.11,<4.0.0)
Requires-Dist: catboost (>=1.1,<2.0)
Requires-Dist: einops (>=0.4.1,<0.5.0)
Requires-Dist: gradio (>=3.7,<4.0)
Requires-Dist: implicit (>=0.6.1,<0.7.0)
Requires-Dist: line-profiler (>=4.0.2,<5.0.0)
Requires-Dist: matplotlib (>=3.5.0,<3.6.0)
Requires-Dist: numba (>=0.56.2,<0.57.0)
Requires-Dist: numpy (>=1.22,<2.0)
Requires-Dist: pandas (>=1.4.0,<2.0.0)
Requires-Dist: protobuf (==3.19.4)
Requires-Dist: pytest (>=7.1.3,<8.0.0)
Requires-Dist: pytorch-lightning (>=1.6,<1.7)
Requires-Dist: scikit-learn (>=1.2.0,<2.0.0)
Requires-Dist: scipy (>=1.7,<2.0)
Requires-Dist: shap (>=0.41.0,<0.42.0)
Requires-Dist: torch (>=1.12.1,<1.13)
Requires-Dist: transformers (>=4.16,<5.0)
Requires-Dist: trash-cli (>=0.22,<0.23)
Requires-Dist: wandb (>=0.13.3,<0.14.0)
